mcd2zarr/__init__.py
mcd2zarr/__main__.py
mcd2zarr/_version.py
mcd2zarr/mcd2zarr.py
mcd2zarr-0.1.0.dist-info/LICENSE
mcd2zarr-0.1.0.dist-info/METADATA
mcd2zarr-0.1.0.dist-info/WHEEL
mcd2zarr-0.1.0.dist-info/entry_points.txt
mcd2zarr-0.1.0.dist-info/top_level.txt
mcd2zarr-0.1.0.dist-info/RECORD
