Metadata-Version: 2.1
Name: mcd2zarr
Version: 0.1.0
Summary: Command line tool to convert MCD files to Zarr
Home-page: https://github.com/BodenmillerGroup/mcd2zarr
Author: Jonas Windhager
Author-email: jonas.windhager@uzh.ch
License: MIT
Classifier: Intended Audience :: Science/Research
Classifier: License :: OSI Approved :: MIT License
Classifier: Operating System :: OS Independent
Classifier: Programming Language :: Python
Classifier: Programming Language :: Python :: 3
Classifier: Programming Language :: Python :: 3.8
Classifier: Programming Language :: Python :: 3.9
Classifier: Programming Language :: Python :: 3.10
Requires-Python: >=3.8
License-File: LICENSE
Requires-Dist: click
Requires-Dist: numpy
Requires-Dist: ome-zarr
Requires-Dist: readimc
Requires-Dist: zarr
